topojoin/__init__.py
topojoin/cli.py
topojoin/helper.py
topojoin/topojoin.py
topojoin-0.3.1.dist-info/entry_points.txt
topojoin-0.3.1.dist-info/LICENSE
topojoin-0.3.1.dist-info/WHEEL
topojoin-0.3.1.dist-info/METADATA
topojoin-0.3.1.dist-info/RECORD
