Metadata-Version: 2.1
Name: topojoin
Version: 0.3.1
Summary: Top-level package for TopoJoin.
Home-page: https://github.com/SimmonsRitchie/topojoin
License: MIT
Author: DSR
Author-email: info@simmonsritchie.com
Requires-Python: >=3.7
Classifier: Development Status :: 4 - Beta
Classifier: Intended Audience :: Developers
Classifier: License :: OSI Approved :: MIT License
Classifier: Natural Language :: English
Classifier: Programming Language :: Python :: 3
Classifier: Programming Language :: Python :: 3.5
Classifier: Programming Language :: Python :: 3.6
Classifier: Programming Language :: Python :: 3.7
Classifier: Programming Language :: Python :: 3.8
Requires-Dist: click
Requires-Dist: importlib_metadata (>=1.7.0,<2.0.0)
